{
  "type": "minecraft:crafting_shapeless",
  "category": "equipment",
  "ingredients": [
    {
      "item": "minecraft:netherite_ingot"
    },
    {
      "item": "minecraft:blaze_rod"
    },
    {
      "item": "minecraft:blaze_rod"
    },
    {
      "item": "minecraft:blaze_rod"
    },
    {
      "item": "minecraft:blaze_rod"
    },
    {
      "item": "minecraft:blaze_rod"
    },
    {
      "item": "minecraft:blaze_rod"
    },
    {
      "item": "minecraft:blaze_rod"
    },
    {
      "item": "minecraft:blaze_rod"
    }
  ],
  "result": {
    "count": 1,
    "id": "cqs_armory:blazing_ingot"
  }
}